dbis_exc_manager-1.0.2.dist-info/licenses/LICENSE
excmanager/Task.py
excmanager/Util.py
excmanager/Version.py
excmanager/__init__.py
excmanager/scorer.py
dbis_exc_manager-1.0.2.dist-info/METADATA
dbis_exc_manager-1.0.2.dist-info/WHEEL
dbis_exc_manager-1.0.2.dist-info/top_level.txt
dbis_exc_manager-1.0.2.dist-info/RECORD
