Metadata-Version: 2.4
Name: dbis-exc-manager
Version: 1.0.2
Summary: RWTH Aachen Computer Science i5/dbis assets for Lecture Datenbanken und Informationssysteme
Author-email: DBIS i5 RWTH Aachen <dbis-vl@dbis.rwth-aachen.de>
License:                                  Apache License
Project-URL: Homepage, https://git.rwth-aachen.de/i5/teaching/dbis/dbis-exercise-manager
Classifier: Programming Language :: Python :: 3.10
Classifier: Programming Language :: Python :: 3.11
Classifier: Programming Language :: Python :: 3.13
Requires-Python: >=3.10
License-File: LICENSE
Requires-Dist: ipython~=8.4
Requires-Dist: Levenshtein~=0.23
Requires-Dist: requests~=2.27
Requires-Dist: tabulate~=0.8
Provides-Extra: test
Requires-Dist: black==23.12.1; extra == "test"
Provides-Extra: build
Requires-Dist: twine==6.*; extra == "build"
Requires-Dist: build==1.*; extra == "build"
Dynamic: license-file
